lissero/__init__.py
lissero/run_lissero.py
lissero/db/lissero.ndb
lissero/db/lissero.nhr
lissero/db/lissero.nin
lissero/db/lissero.nog
lissero/db/lissero.nos
lissero/db/lissero.not
lissero/db/lissero.nsq
lissero/db/lissero.ntf
lissero/db/lissero.nto
lissero/db/lissero_db.json
lissero/db/sequences.fasta
lissero/scripts/Blast.py
lissero/scripts/Sample.py
lissero/scripts/Serotype.py
lissero/scripts/__init__.py
lissero-0.4.9.dist-info/LICENSE
lissero-0.4.9.dist-info/METADATA
lissero-0.4.9.dist-info/WHEEL
lissero-0.4.9.dist-info/entry_points.txt
lissero-0.4.9.dist-info/top_level.txt
lissero-0.4.9.dist-info/RECORD
