Metadata-Version: 2.1
Name: lissero
Version: 0.4.9
Summary: In silico serotyping of Listeria monocytogenes
Home-page: https://github.com/MDU-PHL/lissero
Author: Jason Kwong
Author-email: kwongj@gmail.com
Maintainer: Josh Zhang
Maintainer-email: josh.zhang@unimelb.edu.au
License: UNKNOWN
Project-URL: Bug Reports, https://github.com/MDU-PHL/lissero/issues
Project-URL: Source, https://github.com/MDU-PHL/lissero/
Keywords: Listeria Bioinformatics Serotyping
Platform: UNKNOWN
Classifier: Development Status :: 4 - Beta
Classifier: Intended Audience :: Science/Research
Classifier: Intended Audience :: Healthcare Industry
Classifier: Topic :: Scientific/Engineering :: Bio-Informatics
Classifier: Topic :: Scientific/Engineering :: Medical Science Apps.
Classifier: License :: OSI Approved :: GNU General Public License v3 or later (GPLv3+)
Classifier: Programming Language :: Python :: 3.6
Classifier: Programming Language :: Python :: 3.7
Classifier: Programming Language :: Python :: 3.8
Classifier: Programming Language :: Python :: 3.9
Requires-Python: >=3.6, <4
Requires-Dist: biopython (>=1.77)
Requires-Dist: click (>=7.1.2)
Requires-Dist: loguru (>=0.5.1)
Requires-Dist: numpy (>=1.19.0)
Provides-Extra: dev
Requires-Dist: pre-commit ; extra == 'dev'
Requires-Dist: pipenv ; extra == 'dev'
Provides-Extra: test
Requires-Dist: pytest ; extra == 'test'
Requires-Dist: pytest-cov ; extra == 'test'
